rest_framework_expandable/__init__.py
rest_framework_expandable/fields.py
rest_framework_expandable/serializers.py
rest_framework_expandable/utils.py
rest_framework_expandable/mixins/__init__.py
rest_framework_expandable/mixins/expandable.py
rest_framework_expandable/mixins/expandable_model_serializer.py
rest_framework_expandable/mixins/expandable_related_field.py
django_rest_framework_expandable-0.5.0.dist-info/LICENSE.txt
django_rest_framework_expandable-0.5.0.dist-info/METADATA
django_rest_framework_expandable-0.5.0.dist-info/WHEEL
django_rest_framework_expandable-0.5.0.dist-info/top_level.txt
django_rest_framework_expandable-0.5.0.dist-info/RECORD
