Metadata-Version: 2.1
Name: django-rest-framework-expandable
Version: 0.5.0
Summary: Expandable serializers for Django REST Framework
Home-page: https://github.com/alexseitsinger/django-rest-framework-expandable
Author: Alex Seitsinger
Author-email: software@alexseitsinger.com
License: BSD 2-Clause License
Project-URL: Documentation, https://github.com/alexseitsinger/django-rest-framework-expandable
Project-URL: Source, https://github.com/alexseitsinger/django-rest-framework-expandable
Project-URL: Tracker, https://github.com/alexseitsinger/django-rest-framework-expandable/issues
Keywords: django,rest,djangorestframework
Platform: UNKNOWN
Classifier: Development Status :: 5 - Production/Stable
Classifier: Environment :: Web Environment
Classifier: Framework :: Django
Classifier: Intended Audience :: Developers
Classifier: License :: OSI Approved :: BSD License
Classifier: Natural Language :: English
Classifier: Operating System :: OS Independent
Classifier: Programming Language :: Python :: 2
Classifier: Programming Language :: Python :: 3
Classifier: Topic :: Internet :: WWW/HTTP :: Dynamic Content :: Content Management System
